{
  "totalMentions": 2758,
  "largestAmounts": [
    {
      "raw": "$593,817,000,000",
      "value": 593817000000
    },
    {
      "raw": "$593,817,000,000",
      "value": 593817000000
    },
    {
      "raw": "$550,000,000,000,",
      "value": 550000000000
    },
    {
      "raw": "$550,000,000,000,",
      "value": 550000000000
    },
    {
      "raw": "$508,148,791,000,",
      "value": 508148791000
    },
    {
      "raw": "$508,148,791,000,",
      "value": 508148791000
    },
    {
      "raw": "$400,000,000,000,",
      "value": 400000000000
    },
    {
      "raw": "$400,000,000,000,",
      "value": 400000000000
    },
    {
      "raw": "$316,514,725,000,",
      "value": 316514725000
    },
    {
      "raw": "$316,514,725,000,",
      "value": 316514725000
    },
    {
      "raw": "$74,723,177,000",
      "value": 74723177000
    },
    {
      "raw": "$74,723,177,000",
      "value": 74723177000
    },
    {
      "raw": "$63,396,105,821",
      "value": 63396105821
    },
    {
      "raw": "$63,396,105,821",
      "value": 63396105821
    },
    {
      "raw": "$62,657,105,821",
      "value": 62657105821
    },
    {
      "raw": "$62,657,105,821",
      "value": 62657105821
    },
    {
      "raw": "$61,542,591,000",
      "value": 61542591000
    },
    {
      "raw": "$61,542,591,000",
      "value": 61542591000
    },
    {
      "raw": "$58,249,178,000",
      "value": 58249178000
    },
    {
      "raw": "$58,249,178,000",
      "value": 58249178000
    },
    {
      "raw": "$56,089,818,000",
      "value": 56089818000
    },
    {
      "raw": "$56,089,818,000",
      "value": 56089818000
    },
    {
      "raw": "$54,538,366,000",
      "value": 54538366000
    },
    {
      "raw": "$54,538,366,000",
      "value": 54538366000
    },
    {
      "raw": "$50,614,595,000,",
      "value": 50614595000
    },
    {
      "raw": "$50,614,595,000,",
      "value": 50614595000
    },
    {
      "raw": "$49,452,282,000,",
      "value": 49452282000
    },
    {
      "raw": "$49,452,282,000,",
      "value": 49452282000
    },
    {
      "raw": "$41,770,246,000",
      "value": 41770246000
    },
    {
      "raw": "$41,770,246,000",
      "value": 41770246000
    },
    {
      "raw": "$40,544,559,000",
      "value": 40544559000
    },
    {
      "raw": "$40,544,559,000",
      "value": 40544559000
    },
    {
      "raw": "$38,942,713,000",
      "value": 38942713000
    },
    {
      "raw": "$38,942,713,000",
      "value": 38942713000
    },
    {
      "raw": "$38,768,392,000",
      "value": 38768392000
    },
    {
      "raw": "$38,768,392,000",
      "value": 38768392000
    },
    {
      "raw": "$35,248,875,000,",
      "value": 35248875000
    },
    {
      "raw": "$35,248,875,000,",
      "value": 35248875000
    },
    {
      "raw": "$35,000,000,000",
      "value": 35000000000
    },
    {
      "raw": "$35,000,000,000",
      "value": 35000000000
    },
    {
      "raw": "$34,957,000,000",
      "value": 34957000000
    },
    {
      "raw": "$34,957,000,000",
      "value": 34957000000
    },
    {
      "raw": "$34,438,557,000,",
      "value": 34438557000
    },
    {
      "raw": "$34,438,557,000,",
      "value": 34438557000
    },
    {
      "raw": "$32,605,147,000,",
      "value": 32605147000
    },
    {
      "raw": "$32,605,147,000,",
      "value": 32605147000
    },
    {
      "raw": "$28,099,776,000,",
      "value": 28099776000
    },
    {
      "raw": "$28,099,776,000,",
      "value": 28099776000
    },
    {
      "raw": "$27,151,616,000,",
      "value": 27151616000
    },
    {
      "raw": "$27,151,616,000,",
      "value": 27151616000
    }
  ]
}